{"time": 1586712583809071900, "lat": 32.855415, "lon": -91.022137, "alt": 0, "pol": 0, "mds": 5435, "mcg": 259, "status": 0, "region": 3, "sig": [{"sta": 1175, "time": 3573987, "lat": 42.465519, "lon": -91.879662, "alt": 288, "status": 10}, {"sta": 2155, "time": 3597648, "lat": 37.374611, "lon": -80.521202, "alt": 1183, "status": 12}, {"sta": 1180, "time": 3610819, "lat": 42.284107, "lon": -88.009659, "alt": 237, "status": 10}, {"sta": 2291, "time": 3655565, "lat": 40.887592, "lon": -83.888977, "alt": 255, "status": 12}, {"sta": 2571, "time": 3718890, "lat": 26.688602, "lon": -82.028549, "alt": 9, "status": 4}, {"sta": 1888, "time": 3723467, "lat": 35.662682, "lon": -79.346863, "alt": 176, "status": 12}, {"sta": 2333, "time": 3820447, "lat": 43.068272, "lon": -89.50177, "alt": 325, "status": 4}, {"sta": 2446, "time": 3831636, "lat": 35.956543, "lon": -79.066269, "alt": 175, "status": 12}, {"sta": 1939, "time": 3834141, "lat": 36.049595, "lon": -79.087204, "alt": 213, "status": 12}, {"sta": 1199, "time": 3858851, "lat": 41.491783, "lon": -83.720024, "alt": 185, "status": 10}, {"sta": 2543, "time": 3862001, "lat": 41.491772, "lon": -83.720032, "alt": 187, "status": 12}, {"sta": 2595, "time": 3868501, "lat": 41.684353, "lon": -98.006622, "alt": 552, "status": 12}, {"sta": 934, "time": 4067619, "lat": 43.800545, "lon": -90.073509, "alt": 273, "status": 10}, {"sta": 1955, "time": 4098984, "lat": 26.967613, "lon": -80.097389, "alt": 6, "status": 4}, {"sta": 654, "time": 4122913, "lat": 26.852232, "lon": -80.090805, "alt": 8, "status": 1}, {"sta": 1723, "time": 4172675, "lat": 44.039822, "lon": -92.437653, "alt": 378, "status": 12}, {"sta": 1079, "time": 4204015, "lat": 42.25148, "lon": -83.235085, "alt": 189, "status": 2}, {"sta": 2433, "time": 4255191, "lat": 44.108604, "lon": -93.210236, "alt": 373, "status": 4}, {"sta": 2676, "time": 4262935, "lat": 37.957966, "lon": -78.528862, "alt": 188, "status": 4}, {"sta": 1660, "time": 4275440, "lat": 37.903442, "lon": -78.30706, "alt": 129, "status": 12}, {"sta": 2520, "time": 4301987, "lat": 39.169876, "lon": -78.979736, "alt": 327, "status": 12}, {"sta": 1731, "time": 4336995, "lat": 40.462353, "lon": -79.965828, "alt": 251, "status": 4}, {"sta": 1546, "time": 4337322, "lat": 40.441551, "lon": -79.938202, "alt": 316, "status": 4}, {"sta": 953, "time": 4343877, "lat": 44.295986, "lon": -88.476334, "alt": 250, "status": 2}, {"sta": 1565, "time": 4386190, "lat": 44.437523, "lon": -88.052505, "alt": 194, "status": 4}, {"sta": 976, "time": 4416664, "lat": 44.748081, "lon": -91.553986, "alt": 304, "status": 2}, {"sta": 1505, "time": 4421750, "lat": 44.748085, "lon": -91.553993, "alt": 303, "status": 4}, {"sta": 1189, "time": 4649703, "lat": 38.818291, "lon": -77.419907, "alt": 102, "status": 2}, {"sta": 1451, "time": 4650103, "lat": 38.818298, "lon": -77.419899, "alt": 105, "status": 4}, {"sta": 1750, "time": 4654532, "lat": 45.337063, "lon": -89.485497, "alt": 465, "status": 4}, {"sta": 2351, "time": 4668551, "lat": 39.098309, "lon": -77.522064, "alt": 106, "status": 4}, {"sta": 1170, "time": 4716808, "lat": 38.907112, "lon": -104.845573, "alt": 1981, "status": 2}, {"sta": 1177, "time": 4729378, "lat": 45.39658, "lon": -88.12439, "alt": 287, "status": 2}, {"sta": 2622, "time": 4748846, "lat": 36.824749, "lon": -76.2033, "alt": 3, "status": 4}, {"sta": 2307, "time": 4760406, "lat": 45.557556, "lon": -93.209183, "alt": 298, "status": 4}, {"sta": 2352, "time": 4793781, "lat": 39.143776, "lon": -77.073463, "alt": 159, "status": 4}, {"sta": 1949, "time": 4843002, "lat": 39.642868, "lon": -104.738922, "alt": 1778, "status": 4}, {"sta": 2334, "time": 4881416, "lat": 45.926498, "lon": -89.161942, "alt": 516, "status": 4}, {"sta": 2382, "time": 4884903, "lat": 45.926483, "lon": -89.16198, "alt": 516, "status": 4}, {"sta": 1992, "time": 4897891, "lat": 38.786102, "lon": -90.305962, "alt": 190, "status": 4}], "delay": 7.8}