{"time": 1586712979831726600, "lat": 47.45353, "lon": -0.718584, "alt": 0, "pol": 0, "mds": 10518, "mcg": 137, "status": 0, "region": 1, "sig": [{"sta": 1343, "time": 1690588, "lat": 43.057373, "lon": 0.988286, "alt": 317, "status": 10}, {"sta": 1877, "time": 1708042, "lat": 43.434269, "lon": -3.871711, "alt": 39, "status": 12}, {"sta": 1637, "time": 1733757, "lat": 51.988487, "lon": -2.393044, "alt": 48, "status": 12}, {"sta": 2647, "time": 1753658, "lat": 51.825741, "lon": -3.098863, "alt": 105, "status": 4}, {"sta": 992, "time": 1772966, "lat": 48.652321, "lon": 6.205409, "alt": 218, "status": 10}, {"sta": 2327, "time": 1802800, "lat": 43.443954, "lon": -3.884243, "alt": 41, "status": 4}, {"sta": 733, "time": 1850973, "lat": 50.754189, "lon": 4.982887, "alt": 51, "status": 10}, {"sta": 1744, "time": 1883005, "lat": 46.284237, "lon": 6.308661, "alt": 486, "status": 4}, {"sta": 2274, "time": 1895289, "lat": 51.280663, "lon": 4.420401, "alt": 12, "status": 12}, {"sta": 1273, "time": 1920505, "lat": 52.461922, "lon": -2.167579, "alt": 96, "status": 2}, {"sta": 2645, "time": 1926035, "lat": 52.563351, "lon": -1.359152, "alt": 114, "status": 2}, {"sta": 1622, "time": 1930513, "lat": 52.621422, "lon": -0.28165, "alt": 14, "status": 12}, {"sta": 2470, "time": 1931654, "lat": 51.17382, "lon": 4.828624, "alt": 15, "status": 12}, {"sta": 701, "time": 1937509, "lat": 47.883152, "lon": 6.988247, "alt": 445, "status": 10}, {"sta": 2267, "time": 1947696, "lat": 50.864487, "lon": -1.403687, "alt": 8, "status": 4}, {"sta": 1454, "time": 1950956, "lat": 51.375568, "lon": 4.468174, "alt": 28, "status": 4}, {"sta": 794, "time": 1980094, "lat": 47.063808, "lon": 7.091404, "alt": 451, "status": 10}, {"sta": 2324, "time": 2010023, "lat": 42.373436, "lon": 1.885693, "alt": 1171, "status": 12}, {"sta": 765, "time": 2056310, "lat": 46.837326, "lon": 7.36655, "alt": 751, "status": 10}, {"sta": 2145, "time": 2072589, "lat": 47.359322, "lon": 7.49854, "alt": 576, "status": 12}, {"sta": 786, "time": 2078990, "lat": 46.980431, "lon": 7.489193, "alt": 612, "status": 10}, {"sta": 2102, "time": 2082013, "lat": 46.936268, "lon": 7.474958, "alt": 562, "status": 12}, {"sta": 1152, "time": 2083705, "lat": 51.001751, "lon": 5.901628, "alt": 44, "status": 10}, {"sta": 2275, "time": 2085406, "lat": 46.102905, "lon": 7.210914, "alt": 1618, "status": 12}, {"sta": 1485, "time": 2092986, "lat": 42.679852, "lon": 2.793274, "alt": 73, "status": 4}, {"sta": 304, "time": 2118178, "lat": 50.987849, "lon": 6.315081, "alt": 109, "status": 1}, {"sta": 2060, "time": 2123164, "lat": 46.887306, "lon": 7.627552, "alt": 723, "status": 4}, {"sta": 871, "time": 2165780, "lat": 47.014671, "lon": 7.441885, "alt": 588, "status": 2}, {"sta": 1719, "time": 2178002, "lat": 47.843437, "lon": 7.928197, "alt": 814, "status": 4}, {"sta": 938, "time": 2212862, "lat": 46.710052, "lon": 7.964357, "alt": 579, "status": 2}, {"sta": 2133, "time": 2214181, "lat": 51.31802, "lon": 6.202091, "alt": 49, "status": 4}, {"sta": 751, "time": 2216911, "lat": 46.710052, "lon": 7.964384, "alt": 588, "status": 2}, {"sta": 2315, "time": 2226393, "lat": 52.85284, "lon": -4.645712, "alt": 112, "status": 4}, {"sta": 1071, "time": 2229965, "lat": 46.754662, "lon": 8.029007, "alt": 572, "status": 2}, {"sta": 766, "time": 2240605, "lat": 47.257404, "lon": 8.18442, "alt": 532, "status": 2}, {"sta": 1367, "time": 2249796, "lat": 43.600906, "lon": 5.476528, "alt": 377, "status": 2}, {"sta": 1465, "time": 2250071, "lat": 50.987843, "lon": 6.315059, "alt": 108, "status": 4}, {"sta": 1074, "time": 2265667, "lat": 47.49165, "lon": 8.292652, "alt": 420, "status": 2}, {"sta": 2065, "time": 2278272, "lat": 48.123142, "lon": 8.333979, "alt": 866, "status": 4}, {"sta": 2099, "time": 2291486, "lat": 50.677597, "lon": 7.265352, "alt": 268, "status": 4}], "delay": 7.3}