{"time": 1586711059472654600, "lat": 47.478377, "lon": -0.241594, "alt": 0, "pol": 0, "mds": 8663, "mcg": 121, "status": 0, "region": 1, "sig": [{"sta": 957, "time": 1380895, "lat": 51.083282, "lon": 1.181241, "alt": 16, "status": 10}, {"sta": 2576, "time": 1552231, "lat": 51.647881, "lon": -0.045645, "alt": 24, "status": 12}, {"sta": 992, "time": 1657871, "lat": 48.652321, "lon": 6.205408, "alt": 218, "status": 10}, {"sta": 1637, "time": 1759340, "lat": 51.988487, "lon": -2.393044, "alt": 48, "status": 12}, {"sta": 1073, "time": 1899374, "lat": 45.408825, "lon": 6.558171, "alt": 1337, "status": 10}, {"sta": 765, "time": 1936388, "lat": 46.837326, "lon": 7.366549, "alt": 751, "status": 10}, {"sta": 786, "time": 1958563, "lat": 46.980427, "lon": 7.489192, "alt": 612, "status": 10}, {"sta": 2275, "time": 1969580, "lat": 46.102905, "lon": 7.210914, "alt": 1618, "status": 4}, {"sta": 2060, "time": 2004003, "lat": 46.887306, "lon": 7.627552, "alt": 723, "status": 12}, {"sta": 304, "time": 2052846, "lat": 50.987857, "lon": 6.315085, "alt": 110, "status": 9}, {"sta": 1465, "time": 2059528, "lat": 50.987843, "lon": 6.315059, "alt": 108, "status": 12}, {"sta": 938, "time": 2092157, "lat": 46.710052, "lon": 7.964357, "alt": 579, "status": 10}, {"sta": 1071, "time": 2109094, "lat": 46.754662, "lon": 8.029006, "alt": 572, "status": 10}, {"sta": 766, "time": 2118393, "lat": 47.257404, "lon": 8.18442, "alt": 532, "status": 10}, {"sta": 1671, "time": 2212904, "lat": 47.187054, "lon": 8.460768, "alt": 444, "status": 4}, {"sta": 774, "time": 2365868, "lat": 48.424747, "lon": 9.150818, "alt": 616, "status": 10}, {"sta": 1831, "time": 2487704, "lat": 43.112694, "lon": -7.460509, "alt": 444, "status": 12}, {"sta": 1657, "time": 2778103, "lat": 51.817249, "lon": 8.843394, "alt": 169, "status": 4}, {"sta": 1088, "time": 2867968, "lat": 47.67712, "lon": 11.170131, "alt": 706, "status": 2}], "delay": 7}