{"time": 1586710661532544500, "lat": 39.320785, "lon": -4.567844, "alt": 0, "pol": 0, "mds": 8256, "mcg": 156, "status": 0, "region": 1, "sig": [{"sta": 1948, "time": 783113, "lat": 40.231327, "lon": -2.089708, "alt": 977, "status": 12}, {"sta": 1967, "time": 1021816, "lat": 37.94278, "lon": -7.597114, "alt": 216, "status": 12}, {"sta": 858, "time": 1096336, "lat": 39.589161, "lon": -8.361349, "alt": 68, "status": 10}, {"sta": 1221, "time": 1181578, "lat": 39.546543, "lon": -0.456225, "alt": 114, "status": 10}, {"sta": 1045, "time": 1277276, "lat": 39.226231, "lon": -8.997232, "alt": 128, "status": 10}, {"sta": 1877, "time": 1396163, "lat": 43.434265, "lon": -3.871711, "alt": 39, "status": 4}, {"sta": 1889, "time": 1447009, "lat": 42.520607, "lon": -7.506, "alt": 313, "status": 12}, {"sta": 2607, "time": 1479530, "lat": 41.04953, "lon": 0.105328, "alt": 354, "status": 12}, {"sta": 2327, "time": 1543793, "lat": 43.443954, "lon": -3.884243, "alt": 41, "status": 12}, {"sta": 2324, "time": 2141387, "lat": 42.373436, "lon": 1.885693, "alt": 1171, "status": 12}, {"sta": 1476, "time": 2226926, "lat": 43.343159, "lon": 1.14951, "alt": 248, "status": 4}, {"sta": 1236, "time": 2259059, "lat": 44.146606, "lon": 0.414535, "alt": 131, "status": 10}, {"sta": 1149, "time": 2397736, "lat": 44.019749, "lon": 1.370484, "alt": 110, "status": 10}, {"sta": 1485, "time": 2421517, "lat": 42.679848, "lon": 2.793272, "alt": 73, "status": 4}, {"sta": 1697, "time": 2467249, "lat": 44.793644, "lon": 0.475935, "alt": 156, "status": 10}, {"sta": 819, "time": 2486633, "lat": 42.771931, "lon": 2.998979, "alt": 7, "status": 2}, {"sta": 1391, "time": 2609828, "lat": 45.179245, "lon": 0.65644, "alt": 153, "status": 10}, {"sta": 1373, "time": 2642947, "lat": 45.942734, "lon": -0.979922, "alt": 7, "status": 2}, {"sta": 1104, "time": 2797628, "lat": 45.95718, "lon": 0.252822, "alt": 96, "status": 10}, {"sta": 1291, "time": 3473288, "lat": 47.816597, "lon": 1.049736, "alt": 132, "status": 2}, {"sta": 1744, "time": 3993882, "lat": 46.284237, "lon": 6.308659, "alt": 486, "status": 4}, {"sta": 765, "time": 4318328, "lat": 46.837326, "lon": 7.366549, "alt": 751, "status": 2}, {"sta": 786, "time": 4374520, "lat": 46.980427, "lon": 7.489192, "alt": 612, "status": 2}, {"sta": 1259, "time": 4403470, "lat": 44.785542, "lon": 9.316298, "alt": 1417, "status": 2}, {"sta": 1071, "time": 4441132, "lat": 46.754662, "lon": 8.029006, "alt": 572, "status": 2}, {"sta": 747, "time": 4453461, "lat": 51.011616, "lon": -1.639249, "alt": 56, "status": 2}, {"sta": 2344, "time": 4455776, "lat": 32.663822, "lon": -16.892542, "alt": 379, "status": 4}, {"sta": 2080, "time": 4509295, "lat": 50.929703, "lon": -0.133519, "alt": 45, "status": 4}, {"sta": 871, "time": 4526120, "lat": 47.014668, "lon": 7.441885, "alt": 588, "status": 2}, {"sta": 766, "time": 4579668, "lat": 47.257404, "lon": 8.18442, "alt": 532, "status": 2}, {"sta": 1671, "time": 4637233, "lat": 47.187054, "lon": 8.460768, "alt": 444, "status": 4}, {"sta": 1074, "time": 4649082, "lat": 47.491646, "lon": 8.29265, "alt": 420, "status": 2}, {"sta": 957, "time": 4658924, "lat": 51.083282, "lon": 1.181241, "alt": 16, "status": 2}, {"sta": 800, "time": 4686063, "lat": 43.959385, "lon": 10.953971, "alt": 144, "status": 2}, {"sta": 1443, "time": 4699412, "lat": 43.959999, "lon": 11.147207, "alt": 293, "status": 4}, {"sta": 2576, "time": 4734063, "lat": 51.647881, "lon": -0.045645, "alt": 24, "status": 4}, {"sta": 1989, "time": 4734160, "lat": 47.525246, "lon": 8.659389, "alt": 424, "status": 4}, {"sta": 1968, "time": 4772990, "lat": 51.371201, "lon": 1.301205, "alt": 16, "status": 4}, {"sta": 2447, "time": 4812332, "lat": 51.785275, "lon": -0.187061, "alt": 72, "status": 4}, {"sta": 1562, "time": 4954871, "lat": 47.147087, "lon": 9.431192, "alt": 1414, "status": 4}], "delay": 7.6}