{"time": 1586710696296745000, "lat": 52.348725, "lon": 0.362789, "alt": 0, "pol": 0, "mds": 9577, "mcg": 172, "status": 0, "region": 1, "sig": [{"sta": 1354, "time": 62682, "lat": 52.456066, "lon": 0.057497, "alt": 5, "status": 2}, {"sta": 700, "time": 152302, "lat": 52.108688, "lon": 0.906544, "alt": 43, "status": 10}, {"sta": 1622, "time": 171876, "lat": 52.621418, "lon": -0.281653, "alt": 14, "status": 12}, {"sta": 1819, "time": 235392, "lat": 52.057968, "lon": 1.268417, "alt": 26, "status": 12}, {"sta": 2447, "time": 240339, "lat": 51.785275, "lon": -0.187061, "alt": 72, "status": 12}, {"sta": 2576, "time": 270312, "lat": 51.647881, "lon": -0.045645, "alt": 24, "status": 12}, {"sta": 1608, "time": 314280, "lat": 52.170101, "lon": -1.012069, "alt": 141, "status": 12}, {"sta": 2002, "time": 357385, "lat": 51.527523, "lon": -0.384967, "alt": 31, "status": 4}, {"sta": 1288, "time": 380273, "lat": 51.700832, "lon": -0.908408, "alt": 124, "status": 10}, {"sta": 2413, "time": 382688, "lat": 51.395275, "lon": -0.260615, "alt": 27, "status": 12}, {"sta": 783, "time": 385215, "lat": 51.913029, "lon": -1.154964, "alt": 86, "status": 10}, {"sta": 2645, "time": 391402, "lat": 52.563351, "lon": -1.359151, "alt": 114, "status": 10}, {"sta": 1968, "time": 423895, "lat": 51.371201, "lon": 1.301205, "alt": 16, "status": 12}, {"sta": 843, "time": 454428, "lat": 51.309315, "lon": -0.70603, "alt": 109, "status": 10}, {"sta": 878, "time": 480611, "lat": 51.249134, "lon": -0.774408, "alt": 114, "status": 10}, {"sta": 957, "time": 502591, "lat": 51.083282, "lon": 1.181241, "alt": 16, "status": 10}, {"sta": 217, "time": 513950, "lat": 51.407879, "lon": -1.276797, "alt": 83, "status": 9}, {"sta": 2080, "time": 537142, "lat": 50.929703, "lon": -0.133519, "alt": 45, "status": 12}, {"sta": 1273, "time": 570118, "lat": 52.461922, "lon": -2.16758, "alt": 96, "status": 10}, {"sta": 1637, "time": 636300, "lat": 51.988487, "lon": -2.393044, "alt": 48, "status": 12}, {"sta": 2512, "time": 655038, "lat": 50.915947, "lon": -1.303907, "alt": 29, "status": 12}, {"sta": 747, "time": 673845, "lat": 51.011616, "lon": -1.639249, "alt": 56, "status": 10}, {"sta": 2267, "time": 683833, "lat": 50.864487, "lon": -1.403687, "alt": 8, "status": 12}, {"sta": 2241, "time": 754523, "lat": 51.469337, "lon": -2.573878, "alt": 14, "status": 4}, {"sta": 1620, "time": 755027, "lat": 53.858353, "lon": -1.840078, "alt": 109, "status": 4}, {"sta": 1520, "time": 777883, "lat": 46.621365, "lon": 10.593573, "alt": 909, "status": 4}, {"sta": 1075, "time": 778777, "lat": 53.396526, "lon": -2.669356, "alt": 17, "status": 2}, {"sta": 1472, "time": 809905, "lat": 53.396545, "lon": -2.669359, "alt": 30, "status": 4}, {"sta": 1338, "time": 816634, "lat": 51.362713, "lon": -2.800545, "alt": 16, "status": 2}, {"sta": 2647, "time": 821441, "lat": 51.825741, "lon": -3.098863, "alt": 105, "status": 4}, {"sta": 1344, "time": 907270, "lat": 52.118881, "lon": 4.293329, "alt": 28, "status": 2}, {"sta": 1690, "time": 909809, "lat": 54.61776, "lon": -1.084244, "alt": 12, "status": 4}, {"sta": 1509, "time": 944474, "lat": 50.739548, "lon": -2.753562, "alt": 24, "status": 4}, {"sta": 694, "time": 961769, "lat": 52.071976, "lon": 4.51094, "alt": -7, "status": 2}, {"sta": 1292, "time": 994794, "lat": 51.53479, "lon": 4.44153, "alt": 2, "status": 2}, {"sta": 2518, "time": 995316, "lat": 50.302071, "lon": 3.065227, "alt": 52, "status": 4}, {"sta": 1454, "time": 1024037, "lat": 51.375565, "lon": 4.468177, "alt": 28, "status": 4}, {"sta": 1845, "time": 1038014, "lat": 52.077343, "lon": 4.830536, "alt": -4, "status": 4}, {"sta": 2442, "time": 1040665, "lat": 50.698082, "lon": -3.290698, "alt": 24, "status": 4}, {"sta": 1627, "time": 1101073, "lat": 54.783264, "lon": -2.421839, "alt": 433, "status": 4}], "delay": 4.5}