{"time": 1586712032258337000, "lat": 51.110648, "lon": 3.233921, "alt": 0, "pol": 0, "mds": 4117, "mcg": 151, "status": 0, "region": 1, "sig": [{"sta": 1026, "time": 1239077, "lat": 51.743553, "lon": 8.518283, "alt": 86, "status": 2}, {"sta": 1052, "time": 1242751, "lat": 52.577156, "lon": 8.137508, "alt": 41, "status": 2}, {"sta": 627, "time": 1243614, "lat": 52.003881, "lon": 8.432157, "alt": 116, "status": 9}, {"sta": 1657, "time": 1322469, "lat": 51.817253, "lon": 8.843394, "alt": 169, "status": 12}, {"sta": 1273, "time": 1333964, "lat": 52.461922, "lon": -2.167579, "alt": 96, "status": 10}, {"sta": 1637, "time": 1336989, "lat": 51.988487, "lon": -2.393044, "alt": 48, "status": 12}, {"sta": 1798, "time": 1348292, "lat": 49.403488, "lon": 8.247619, "alt": 114, "status": 12}, {"sta": 1811, "time": 1369663, "lat": 52.015343, "lon": 8.714627, "alt": 108, "status": 4}, {"sta": 1247, "time": 1403515, "lat": 52.169891, "lon": 9.100227, "alt": 61, "status": 10}, {"sta": 1509, "time": 1406970, "lat": 50.739548, "lon": -2.753562, "alt": 24, "status": 12}, {"sta": 1606, "time": 1446458, "lat": 51.913475, "lon": 9.357175, "alt": 232, "status": 4}, {"sta": 1547, "time": 1453655, "lat": 51.942844, "lon": 9.402626, "alt": 307, "status": 10}, {"sta": 2256, "time": 1456015, "lat": 51.299049, "lon": 9.474239, "alt": 180, "status": 4}, {"sta": 2647, "time": 1491599, "lat": 51.825741, "lon": -3.098863, "alt": 105, "status": 4}, {"sta": 1609, "time": 1513587, "lat": 53.194637, "lon": 8.534795, "alt": 12, "status": 4}, {"sta": 2442, "time": 1533193, "lat": 50.698082, "lon": -3.290698, "alt": 25, "status": 12}, {"sta": 1532, "time": 1536223, "lat": 50.884151, "lon": -3.373754, "alt": 80, "status": 4}, {"sta": 1620, "time": 1538092, "lat": 53.858353, "lon": -1.840078, "alt": 109, "status": 4}, {"sta": 2137, "time": 1569060, "lat": 49.768456, "lon": 8.635623, "alt": 134, "status": 4}, {"sta": 785, "time": 1572108, "lat": 53.799629, "lon": 8.618088, "alt": 10, "status": 10}, {"sta": 1075, "time": 1583642, "lat": 53.396526, "lon": -2.669355, "alt": 17, "status": 10}, {"sta": 715, "time": 1590385, "lat": 52.481293, "lon": 9.80237, "alt": 44, "status": 10}, {"sta": 1472, "time": 1616331, "lat": 53.396545, "lon": -2.669358, "alt": 30, "status": 4}, {"sta": 1690, "time": 1621886, "lat": 54.61776, "lon": -1.084244, "alt": 12, "status": 12}, {"sta": 1805, "time": 1637063, "lat": 48.597916, "lon": 8.855436, "alt": 451, "status": 4}, {"sta": 2065, "time": 1650988, "lat": 48.12318, "lon": 8.334015, "alt": 860, "status": 4}, {"sta": 829, "time": 1710339, "lat": 48.308289, "lon": 8.913764, "alt": 564, "status": 2}, {"sta": 774, "time": 1727454, "lat": 48.42474, "lon": 9.150817, "alt": 615, "status": 2}, {"sta": 931, "time": 1728073, "lat": 48.797325, "lon": 9.526278, "alt": 285, "status": 2}, {"sta": 944, "time": 1737654, "lat": 53.522251, "lon": 9.80588, "alt": 1, "status": 2}, {"sta": 1074, "time": 1812357, "lat": 47.491646, "lon": 8.292652, "alt": 420, "status": 2}, {"sta": 1938, "time": 1837915, "lat": 50.947659, "lon": 11.092357, "alt": 270, "status": 4}, {"sta": 1645, "time": 1845759, "lat": 54.994591, "lon": -1.787593, "alt": 120, "status": 4}, {"sta": 766, "time": 1860386, "lat": 47.257404, "lon": 8.18442, "alt": 532, "status": 2}, {"sta": 1989, "time": 1867939, "lat": 47.525246, "lon": 8.659389, "alt": 424, "status": 4}, {"sta": 765, "time": 1872524, "lat": 46.837326, "lon": 7.36655, "alt": 751, "status": 2}, {"sta": 1102, "time": 1882595, "lat": 50.364067, "lon": 11.153777, "alt": 379, "status": 2}, {"sta": 1633, "time": 1886123, "lat": 50.901089, "lon": 11.286111, "alt": 272, "status": 4}, {"sta": 2060, "time": 1897333, "lat": 46.887306, "lon": 7.627552, "alt": 723, "status": 4}, {"sta": 1671, "time": 1944501, "lat": 47.187054, "lon": 8.460768, "alt": 444, "status": 4}], "delay": 7.8}