{"time": 1586712104318043000, "lat": 28.137279, "lon": 125.269623, "alt": 0, "pol": 0, "mds": 8052, "mcg": 249, "status": 0, "region": 4, "sig": [{"sta": 1721, "time": 5350600, "lat": 35.714935, "lon": 139.762466, "alt": 35, "status": 12}, {"sta": 1530, "time": 5378960, "lat": 35.652386, "lon": 139.774734, "alt": 38, "status": 4}, {"sta": 1783, "time": 5434635, "lat": 35.891926, "lon": 139.967743, "alt": 20, "status": 12}, {"sta": 1566, "time": 5510132, "lat": 35.740265, "lon": 140.345688, "alt": 37, "status": 12}, {"sta": 2035, "time": 5614422, "lat": 37.896488, "lon": 139.101822, "alt": 7, "status": 12}, {"sta": 1997, "time": 5670335, "lat": 36.930813, "lon": 140.015579, "alt": 284, "status": 4}, {"sta": 1720, "time": 5885099, "lat": 37.012836, "lon": 140.914337, "alt": 63, "status": 12}, {"sta": 2149, "time": 6241945, "lat": 38.426006, "lon": 141.237152, "alt": 10, "status": 12}, {"sta": 1922, "time": 7249382, "lat": 42.623497, "lon": 141.49498, "alt": 17, "status": 12}, {"sta": 2150, "time": 7327828, "lat": 42.81786, "lon": 141.625336, "alt": 20, "status": 12}, {"sta": 1666, "time": 7334236, "lat": 43.072617, "lon": 141.339401, "alt": 26, "status": 12}, {"sta": 1924, "time": 7888707, "lat": 44.374142, "lon": 142.482727, "alt": 158, "status": 12}, {"sta": 1923, "time": 8086046, "lat": 43.822876, "lon": 143.905243, "alt": 119, "status": 4}, {"sta": 1893, "time": 8476711, "lat": 31.598206, "lon": 130.507156, "alt": 125, "status": 4}, {"sta": 1999, "time": 8581283, "lat": 13.357628, "lon": 144.750488, "alt": 107, "status": 4}, {"sta": 2582, "time": 10989656, "lat": 24.905031, "lon": 91.883949, "alt": 25, "status": 4}, {"sta": 1569, "time": 14813759, "lat": 45.284779, "lon": 79.358025, "alt": 954, "status": 10}, {"sta": 1357, "time": 15050722, "lat": 45.002628, "lon": 78.40451, "alt": 620, "status": 10}, {"sta": 1558, "time": 15347260, "lat": 43.042946, "lon": 76.944366, "alt": 3345, "status": 10}], "delay": 5}