{"time": 1586711885608005400, "lat": 52.913951, "lon": 9.322469, "alt": 0, "pol": 0, "mds": 10446, "mcg": 202, "status": 0, "region": 1, "sig": [{"sta": 735, "time": 922369, "lat": 51.300495, "lon": 12.40329, "alt": 137, "status": 10}, {"sta": 271, "time": 988906, "lat": 52.015325, "lon": 8.714627, "alt": 111, "status": 1}, {"sta": 402, "time": 1001952, "lat": 50.987847, "lon": 6.315069, "alt": 106, "status": 9}, {"sta": 257, "time": 1020633, "lat": 52.65777, "lon": 4.83899, "alt": -2, "status": 9}, {"sta": 1663, "time": 1051269, "lat": 50.272289, "lon": 7.833576, "alt": 298, "status": 4}, {"sta": 43, "time": 1068415, "lat": 53.182147, "lon": 8.63905, "alt": 23, "status": 1}, {"sta": 1594, "time": 1073548, "lat": 55.62534, "lon": 11.837313, "alt": 34, "status": 4}, {"sta": 327, "time": 1079185, "lat": 50.627534, "lon": 6.47034, "alt": 264, "status": 9}, {"sta": 2253, "time": 1104607, "lat": 56.084888, "lon": 9.904555, "alt": 85, "status": 4}, {"sta": 383, "time": 1118987, "lat": 51.116128, "lon": 13.621944, "alt": 198, "status": 1}, {"sta": 1129, "time": 1123465, "lat": 51.869858, "lon": 13.961437, "alt": 48, "status": 10}, {"sta": 1665, "time": 1164369, "lat": 49.960018, "lon": 10.996869, "alt": 282, "status": 12}, {"sta": 380, "time": 1167374, "lat": 51.454855, "lon": 13.861905, "alt": 108, "status": 9}, {"sta": 252, "time": 1173797, "lat": 50.741545, "lon": 4.830526, "alt": 74, "status": 1}, {"sta": 325, "time": 1179456, "lat": 51.918834, "lon": 4.411041, "alt": 10, "status": 9}, {"sta": 154, "time": 1239157, "lat": 51.005727, "lon": 13.763956, "alt": 188, "status": 9}, {"sta": 2654, "time": 1245338, "lat": 50.555981, "lon": 13.162287, "alt": 580, "status": 12}, {"sta": 2, "time": 1253642, "lat": 49.710379, "lon": 10.896895, "alt": 275, "status": 9}, {"sta": 258, "time": 1273955, "lat": 49.605364, "lon": 10.884013, "alt": 354, "status": 1}, {"sta": 1686, "time": 1312004, "lat": 49.42297, "lon": 8.418813, "alt": 94, "status": 12}, {"sta": 524, "time": 1314654, "lat": 52.151853, "lon": 10.316725, "alt": 88, "status": 1}, {"sta": 899, "time": 1450646, "lat": 51.043068, "lon": 3.746718, "alt": 6, "status": 10}, {"sta": 29, "time": 1551738, "lat": 49.700325, "lon": 10.7696, "alt": 288, "status": 1}, {"sta": 750, "time": 1574970, "lat": 48.353439, "lon": 9.247942, "alt": 747, "status": 2}, {"sta": 1755, "time": 1593054, "lat": 51.091808, "lon": 14.467221, "alt": 265, "status": 4}, {"sta": 1493, "time": 1627557, "lat": 50.733795, "lon": 3.180325, "alt": 34, "status": 4}, {"sta": 1038, "time": 1651321, "lat": 48.462772, "lon": 9.22887, "alt": 437, "status": 2}, {"sta": 2503, "time": 2033119, "lat": 6.42436, "lon": 3.410408, "alt": 19, "status": 4}, {"sta": 1455, "time": 2094248, "lat": 49.355671, "lon": 2.393032, "alt": 142, "status": 4}, {"sta": 786, "time": 2170092, "lat": 46.980431, "lon": 7.489192, "alt": 612, "status": 2}, {"sta": 1088, "time": 2176107, "lat": 47.67712, "lon": 11.170131, "alt": 706, "status": 2}, {"sta": 751, "time": 2208343, "lat": 46.710052, "lon": 7.964383, "alt": 588, "status": 2}, {"sta": 516, "time": 2244754, "lat": 47.843433, "lon": 7.928189, "alt": 782, "status": 1}, {"sta": 834, "time": 2249700, "lat": 46.975868, "lon": 7.423939, "alt": 542, "status": 2}, {"sta": 2413, "time": 2257086, "lat": 51.395275, "lon": -0.260615, "alt": 27, "status": 4}, {"sta": 765, "time": 2301212, "lat": 46.837326, "lon": 7.36655, "alt": 751, "status": 2}, {"sta": 1806, "time": 2310740, "lat": 48.990963, "lon": 1.719239, "alt": 37, "status": 4}, {"sta": 1108, "time": 2343629, "lat": 46.700909, "lon": 7.894098, "alt": 606, "status": 2}, {"sta": 1681, "time": 2357529, "lat": 48.876869, "lon": 15.136164, "alt": 569, "status": 4}, {"sta": 843, "time": 2362218, "lat": 51.309315, "lon": -0.70603, "alt": 109, "status": 2}], "delay": 7.5}