{"time": 1586713189230220500, "lat": 33.34688, "lon": -4.651943, "alt": 0, "pol": 0, "mds": 11393, "mcg": 194, "status": 0, "region": 1, "sig": [{"sta": 1045, "time": 2501768, "lat": 39.226231, "lon": -8.997233, "alt": 128, "status": 2}, {"sta": 2338, "time": 2808578, "lat": 40.594322, "lon": -1.907545, "alt": 1198, "status": 12}, {"sta": 1831, "time": 3673692, "lat": 43.112694, "lon": -7.460509, "alt": 444, "status": 4}, {"sta": 1877, "time": 3749573, "lat": 43.434269, "lon": -3.871711, "alt": 39, "status": 12}, {"sta": 2344, "time": 3818391, "lat": 32.663822, "lon": -16.892542, "alt": 379, "status": 12}, {"sta": 1836, "time": 4576545, "lat": 28.65378, "lon": -17.885185, "alt": 624, "status": 4}, {"sta": 1073, "time": 5490665, "lat": 45.408825, "lon": 6.558172, "alt": 1337, "status": 10}, {"sta": 1251, "time": 5687612, "lat": 38.072258, "lon": 13.343636, "alt": 164, "status": 10}, {"sta": 2615, "time": 5916288, "lat": 35.875687, "lon": 14.525917, "alt": 57, "status": 12}, {"sta": 806, "time": 5953599, "lat": 41.464909, "lon": 12.895183, "alt": 33, "status": 2}, {"sta": 1132, "time": 6005307, "lat": 41.790455, "lon": 12.871634, "alt": 361, "status": 10}, {"sta": 1532, "time": 6504150, "lat": 50.884151, "lon": -3.373753, "alt": 80, "status": 4}, {"sta": 2267, "time": 6555045, "lat": 50.864487, "lon": -1.403687, "alt": 8, "status": 12}, {"sta": 1911, "time": 6696221, "lat": 40.204536, "lon": 44.485241, "alt": 1082, "status": 4}, {"sta": 2137, "time": 7167527, "lat": 49.768456, "lon": 8.635623, "alt": 134, "status": 4}, {"sta": 2455, "time": 7184038, "lat": 45.856636, "lon": 14.678583, "alt": 458, "status": 12}, {"sta": 2480, "time": 7225774, "lat": 46.033855, "lon": 14.709696, "alt": 648, "status": 12}, {"sta": 1963, "time": 7551276, "lat": 46.614513, "lon": 15.670079, "alt": 277, "status": 12}, {"sta": 1885, "time": 7766299, "lat": 45.330112, "lon": 17.706785, "alt": 222, "status": 12}, {"sta": 1269, "time": 8050713, "lat": 48.149185, "lon": 16.283762, "alt": 224, "status": 2}, {"sta": 2116, "time": 8070502, "lat": 48.379868, "lon": 16.324532, "alt": 190, "status": 4}, {"sta": 2661, "time": 8505518, "lat": 47.93663, "lon": 18.921772, "alt": 865, "status": 12}], "delay": 5.9}