{"time": 1586713225745716000, "lat": 41.763549, "lon": -6.555821, "alt": 0, "pol": 0, "mds": 4929, "mcg": 181, "status": 0, "region": 1, "sig": [{"sta": 2555, "time": 511466, "lat": 41.545403, "lon": -4.703388, "alt": 737, "status": 4}, {"sta": 1914, "time": 741730, "lat": 40.49107, "lon": -8.57933, "alt": 68, "status": 4}, {"sta": 2627, "time": 940036, "lat": 40.336426, "lon": -3.75343, "alt": 660, "status": 4}, {"sta": 858, "time": 953225, "lat": 39.589161, "lon": -8.361347, "alt": 68, "status": 10}, {"sta": 1877, "time": 957366, "lat": 43.434269, "lon": -3.871711, "alt": 39, "status": 12}, {"sta": 2327, "time": 958535, "lat": 43.443954, "lon": -3.884243, "alt": 41, "status": 12}, {"sta": 1045, "time": 1165207, "lat": 39.226231, "lon": -8.997233, "alt": 128, "status": 10}, {"sta": 862, "time": 1348748, "lat": 38.646236, "lon": -9.025767, "alt": 25, "status": 10}, {"sta": 2338, "time": 1362622, "lat": 40.594322, "lon": -1.907545, "alt": 1198, "status": 4}, {"sta": 1948, "time": 1372736, "lat": 40.231331, "lon": -2.089708, "alt": 977, "status": 12}, {"sta": 1967, "time": 1450189, "lat": 37.94278, "lon": -7.597115, "alt": 216, "status": 12}, {"sta": 1846, "time": 1584823, "lat": 37.961327, "lon": -8.870075, "alt": 58, "status": 4}, {"sta": 2607, "time": 1872541, "lat": 41.04953, "lon": 0.105328, "alt": 354, "status": 12}, {"sta": 1221, "time": 1903433, "lat": 39.546543, "lon": -0.456225, "alt": 114, "status": 10}, {"sta": 2078, "time": 1963799, "lat": 36.847073, "lon": -4.003817, "alt": 681, "status": 12}, {"sta": 1236, "time": 2085107, "lat": 44.146606, "lon": 0.414535, "alt": 131, "status": 10}, {"sta": 1343, "time": 2122680, "lat": 43.057373, "lon": 0.988286, "alt": 317, "status": 10}, {"sta": 1373, "time": 2148859, "lat": 45.942734, "lon": -0.979919, "alt": 7, "status": 10}, {"sta": 1697, "time": 2205972, "lat": 44.79364, "lon": 0.475935, "alt": 156, "status": 10}, {"sta": 1476, "time": 2219467, "lat": 43.343163, "lon": 1.14951, "alt": 248, "status": 4}, {"sta": 1442, "time": 2258585, "lat": 46.460979, "lon": -1.158075, "alt": 7, "status": 10}, {"sta": 2401, "time": 2267560, "lat": 45.761856, "lon": -0.158236, "alt": 79, "status": 10}, {"sta": 1786, "time": 2298250, "lat": 44.126312, "lon": 1.240387, "alt": 190, "status": 4}, {"sta": 1391, "time": 2317784, "lat": 45.179245, "lon": 0.656442, "alt": 153, "status": 10}, {"sta": 2324, "time": 2338886, "lat": 42.373436, "lon": 1.885692, "alt": 1171, "status": 4}, {"sta": 1104, "time": 2390734, "lat": 45.957184, "lon": 0.25282, "alt": 96, "status": 2}, {"sta": 2316, "time": 2406063, "lat": 41.508293, "lon": 2.0915, "alt": 193, "status": 4}, {"sta": 1485, "time": 2596855, "lat": 42.679852, "lon": 2.793274, "alt": 73, "status": 4}, {"sta": 1843, "time": 2610593, "lat": 43.518284, "lon": 2.407439, "alt": 352, "status": 4}, {"sta": 788, "time": 2876442, "lat": 39.317173, "lon": 3.134734, "alt": 47, "status": 2}, {"sta": 1291, "time": 3008872, "lat": 47.816597, "lon": 1.049739, "alt": 131, "status": 2}, {"sta": 1377, "time": 3128458, "lat": 46.132687, "lon": 3.458048, "alt": 278, "status": 2}, {"sta": 1615, "time": 3153016, "lat": 44.697208, "lon": 4.302916, "alt": 790, "status": 4}, {"sta": 2442, "time": 3421159, "lat": 50.698082, "lon": -3.290698, "alt": 25, "status": 4}, {"sta": 1532, "time": 3479621, "lat": 50.884151, "lon": -3.373753, "alt": 80, "status": 4}, {"sta": 1806, "time": 3484295, "lat": 48.990963, "lon": 1.719242, "alt": 37, "status": 4}, {"sta": 975, "time": 3492112, "lat": 48.803886, "lon": 2.104583, "alt": 117, "status": 2}, {"sta": 1119, "time": 3501486, "lat": 48.834129, "lon": 2.121251, "alt": 154, "status": 2}, {"sta": 2321, "time": 3511334, "lat": 50.877388, "lon": -2.949747, "alt": 97, "status": 4}, {"sta": 2267, "time": 3627453, "lat": 50.864487, "lon": -1.403687, "alt": 8, "status": 4}], "delay": 8.1}