{"time": 1586713021800828400, "lat": 52.398424, "lon": 0.621158, "alt": 0, "pol": 0, "mds": 10109, "mcg": 82, "status": 0, "region": 1, "sig": [{"sta": 1509, "time": 991939, "lat": 50.739548, "lon": -2.753562, "alt": 24, "status": 12}, {"sta": 1094, "time": 1019897, "lat": 54.215652, "lon": -2.893134, "alt": 22, "status": 10}, {"sta": 2470, "time": 1032000, "lat": 51.17382, "lon": 4.828624, "alt": 15, "status": 4}, {"sta": 1532, "time": 1035594, "lat": 50.884151, "lon": -3.373753, "alt": 80, "status": 4}, {"sta": 2274, "time": 1121803, "lat": 51.280663, "lon": 4.420401, "alt": 12, "status": 4}, {"sta": 1271, "time": 1133209, "lat": 51.781055, "lon": 5.518499, "alt": 4, "status": 10}, {"sta": 252, "time": 1136902, "lat": 50.741517, "lon": 4.830615, "alt": 86, "status": 1}, {"sta": 1440, "time": 1144054, "lat": 50.74139, "lon": 4.830495, "alt": 87, "status": 12}, {"sta": 2315, "time": 1194738, "lat": 52.85284, "lon": -4.645712, "alt": 112, "status": 12}, {"sta": 2421, "time": 1368770, "lat": 49.106987, "lon": 3.352582, "alt": 125, "status": 10}, {"sta": 304, "time": 1376590, "lat": 50.987848, "lon": 6.31508, "alt": 109, "status": 1}, {"sta": 1465, "time": 1404766, "lat": 50.987843, "lon": 6.315059, "alt": 108, "status": 12}, {"sta": 2148, "time": 1414722, "lat": 51.125767, "lon": 6.437602, "alt": 64, "status": 12}, {"sta": 1478, "time": 1540583, "lat": 51.419777, "lon": 6.864884, "alt": 77, "status": 2}, {"sta": 1498, "time": 1576339, "lat": 51.409821, "lon": 7.324663, "alt": 187, "status": 12}, {"sta": 994, "time": 1628075, "lat": 51.407856, "lon": 7.208133, "alt": 131, "status": 2}, {"sta": 2099, "time": 1659945, "lat": 50.677597, "lon": 7.265352, "alt": 268, "status": 12}, {"sta": 1026, "time": 1810724, "lat": 51.743553, "lon": 8.518282, "alt": 86, "status": 10}, {"sta": 1609, "time": 1883624, "lat": 53.194637, "lon": 8.534795, "alt": 12, "status": 4}, {"sta": 992, "time": 1906231, "lat": 48.652321, "lon": 6.205409, "alt": 218, "status": 10}, {"sta": 1606, "time": 2046245, "lat": 51.913475, "lon": 9.357175, "alt": 232, "status": 4}, {"sta": 1547, "time": 2105984, "lat": 51.942844, "lon": 9.402626, "alt": 307, "status": 2}, {"sta": 702, "time": 2517172, "lat": 58.549606, "lon": 5.758182, "alt": 9, "status": 10}, {"sta": 774, "time": 2535894, "lat": 48.424732, "lon": 9.150817, "alt": 614, "status": 2}, {"sta": 1989, "time": 2684575, "lat": 47.525246, "lon": 8.659389, "alt": 424, "status": 4}, {"sta": 751, "time": 2750932, "lat": 46.710052, "lon": 7.964384, "alt": 588, "status": 2}, {"sta": 2625, "time": 2998853, "lat": 56.155025, "lon": 12.68862, "alt": 16, "status": 4}, {"sta": 1088, "time": 3065390, "lat": 47.67712, "lon": 11.170131, "alt": 706, "status": 2}, {"sta": 2240, "time": 3415678, "lat": 52.867603, "lon": 15.53619, "alt": 79, "status": 4}, {"sta": 2507, "time": 3724713, "lat": 52.464085, "lon": 16.942665, "alt": 107, "status": 4}, {"sta": 1681, "time": 3752293, "lat": 48.876869, "lon": 15.136164, "alt": 569, "status": 4}, {"sta": 1188, "time": 4265335, "lat": 43.785927, "lon": -79.366585, "alt": 157, "status": 2}], "delay": 7.4}