{"time": 1586711376539058200, "lat": 38.37602, "lon": -7.070885, "alt": 0, "pol": 0, "mds": 6854, "mcg": 162, "status": 0, "region": 1, "sig": [{"sta": 1914, "time": 895771, "lat": 40.49107, "lon": -8.579331, "alt": 68, "status": 12}, {"sta": 2627, "time": 1114634, "lat": 40.336452, "lon": -3.753486, "alt": 664, "status": 4}, {"sta": 1889, "time": 1530043, "lat": 42.520607, "lon": -7.506, "alt": 313, "status": 4}, {"sta": 1948, "time": 1579792, "lat": 40.231331, "lon": -2.089708, "alt": 977, "status": 12}, {"sta": 1221, "time": 1949714, "lat": 39.546543, "lon": -0.456225, "alt": 114, "status": 10}, {"sta": 2607, "time": 2270016, "lat": 41.04953, "lon": 0.105328, "alt": 354, "status": 12}, {"sta": 788, "time": 2920675, "lat": 39.317173, "lon": 3.134734, "alt": 47, "status": 2}, {"sta": 2324, "time": 2928154, "lat": 42.373436, "lon": 1.885693, "alt": 1171, "status": 12}, {"sta": 1476, "time": 2976562, "lat": 43.343159, "lon": 1.14951, "alt": 248, "status": 4}, {"sta": 1236, "time": 2980732, "lat": 44.146606, "lon": 0.414535, "alt": 131, "status": 10}, {"sta": 1634, "time": 3141789, "lat": 43.411186, "lon": 1.71218, "alt": 183, "status": 4}, {"sta": 1786, "time": 3147314, "lat": 44.126312, "lon": 1.240387, "alt": 190, "status": 12}, {"sta": 1697, "time": 3161630, "lat": 44.793644, "lon": 0.475935, "alt": 156, "status": 10}, {"sta": 1485, "time": 3202105, "lat": 42.679848, "lon": 2.793272, "alt": 73, "status": 12}, {"sta": 2401, "time": 3254783, "lat": 45.761856, "lon": -0.158236, "alt": 79, "status": 2}, {"sta": 819, "time": 3267551, "lat": 42.771931, "lon": 2.998979, "alt": 7, "status": 10}, {"sta": 1843, "time": 3301325, "lat": 43.51828, "lon": 2.407439, "alt": 352, "status": 4}, {"sta": 2398, "time": 3365683, "lat": 45.743275, "lon": 0.120342, "alt": 42, "status": 10}, {"sta": 1442, "time": 3399477, "lat": 46.460979, "lon": -1.158076, "alt": 7, "status": 10}, {"sta": 1104, "time": 3447716, "lat": 45.95718, "lon": 0.252822, "alt": 96, "status": 2}, {"sta": 2293, "time": 3581287, "lat": 45.937538, "lon": 1.049824, "alt": 275, "status": 12}, {"sta": 2344, "time": 3639866, "lat": 32.663822, "lon": -16.892542, "alt": 379, "status": 12}, {"sta": 2330, "time": 3749985, "lat": 48.022881, "lon": -3.450018, "alt": 93, "status": 2}, {"sta": 1430, "time": 3788609, "lat": 46.151764, "lon": 1.910707, "alt": 420, "status": 10}, {"sta": 507, "time": 3924317, "lat": 45.772156, "lon": 2.964538, "alt": 1463, "status": 1}, {"sta": 2258, "time": 3943463, "lat": 46.780979, "lon": 1.802112, "alt": 163, "status": 2}, {"sta": 1615, "time": 3947859, "lat": 44.697208, "lon": 4.302915, "alt": 790, "status": 4}, {"sta": 523, "time": 3964182, "lat": 43.221604, "lon": 5.534146, "alt": 89, "status": 1}, {"sta": 1487, "time": 3998095, "lat": 43.511433, "lon": 5.484964, "alt": 155, "status": 4}, {"sta": 1367, "time": 4006531, "lat": 43.600903, "lon": 5.476527, "alt": 377, "status": 2}, {"sta": 1201, "time": 4166083, "lat": 45.519554, "lon": 4.602533, "alt": 291, "status": 2}, {"sta": 1241, "time": 4304133, "lat": 45.335632, "lon": 5.41668, "alt": 420, "status": 2}, {"sta": 1223, "time": 4330693, "lat": 45.942638, "lon": 4.733397, "alt": 186, "status": 2}, {"sta": 2004, "time": 4382973, "lat": 50.145969, "lon": -5.621422, "alt": 155, "status": 4}, {"sta": 726, "time": 4386426, "lat": 45.218319, "lon": 5.862195, "alt": 222, "status": 2}, {"sta": 1231, "time": 4468340, "lat": 43.721619, "lon": 7.24293, "alt": 188, "status": 2}, {"sta": 1233, "time": 4558329, "lat": 44.087154, "lon": 7.252826, "alt": 1117, "status": 2}, {"sta": 1073, "time": 4570903, "lat": 45.408825, "lon": 6.558171, "alt": 1337, "status": 2}, {"sta": 975, "time": 4577610, "lat": 48.803886, "lon": 2.104583, "alt": 117, "status": 2}, {"sta": 1806, "time": 4585763, "lat": 48.990959, "lon": 1.719239, "alt": 37, "status": 4}], "delay": 8.1}