{"time": 1586711746786845000, "lat": 33.936493, "lon": -88.569292, "alt": 0, "pol": 0, "mds": 3778, "mcg": 219, "status": 0, "region": 3, "sig": [{"sta": 799, "time": 835296, "lat": 35.726902, "lon": -86.886856, "alt": 238, "status": 2}, {"sta": 791, "time": 1946881, "lat": 38.221161, "lon": -84.817444, "alt": 223, "status": 10}, {"sta": 689, "time": 1947591, "lat": 38.221134, "lon": -84.817436, "alt": 226, "status": 10}, {"sta": 1439, "time": 1950451, "lat": 38.221153, "lon": -84.817429, "alt": 222, "status": 12}, {"sta": 2561, "time": 2070009, "lat": 36.552223, "lon": -82.523804, "alt": 381, "status": 4}, {"sta": 2348, "time": 2292752, "lat": 36.044533, "lon": -95.697792, "alt": 200, "status": 4}, {"sta": 1823, "time": 2303582, "lat": 40.133369, "lon": -88.207466, "alt": 230, "status": 12}, {"sta": 728, "time": 2383316, "lat": 40.045174, "lon": -86.094696, "alt": 262, "status": 10}, {"sta": 1178, "time": 2392442, "lat": 29.671406, "lon": -82.701393, "alt": 31, "status": 2}, {"sta": 1952, "time": 2566750, "lat": 33.068378, "lon": -96.703217, "alt": 197, "status": 4}, {"sta": 1860, "time": 2590247, "lat": 29.542299, "lon": -95.105453, "alt": 3, "status": 4}, {"sta": 1648, "time": 2833917, "lat": 28.19636, "lon": -82.684845, "alt": 13, "status": 12}, {"sta": 1888, "time": 2880093, "lat": 35.662682, "lon": -79.346863, "alt": 176, "status": 12}, {"sta": 1824, "time": 2894152, "lat": 29.854717, "lon": -96.527451, "alt": 94, "status": 4}, {"sta": 681, "time": 2959392, "lat": 41.91127, "lon": -88.357269, "alt": 234, "status": 10}, {"sta": 2446, "time": 2984167, "lat": 35.956543, "lon": -79.066269, "alt": 175, "status": 12}, {"sta": 1939, "time": 2984945, "lat": 36.049595, "lon": -79.087204, "alt": 213, "status": 12}, {"sta": 1745, "time": 3010497, "lat": 29.670712, "lon": -96.829765, "alt": 106, "status": 4}, {"sta": 2564, "time": 3048224, "lat": 35.621754, "lon": -78.760498, "alt": 122, "status": 4}, {"sta": 1199, "time": 3141874, "lat": 41.491783, "lon": -83.720024, "alt": 185, "status": 10}, {"sta": 2543, "time": 3143986, "lat": 41.491772, "lon": -83.720024, "alt": 187, "status": 12}, {"sta": 1175, "time": 3348755, "lat": 42.465519, "lon": -91.879662, "alt": 288, "status": 2}, {"sta": 2333, "time": 3402013, "lat": 43.068272, "lon": -89.50177, "alt": 324, "status": 12}, {"sta": 1660, "time": 3416492, "lat": 37.903442, "lon": -78.30706, "alt": 129, "status": 12}, {"sta": 2520, "time": 3453468, "lat": 39.169876, "lon": -78.979736, "alt": 327, "status": 4}, {"sta": 1731, "time": 3547971, "lat": 40.462353, "lon": -79.965828, "alt": 251, "status": 4}, {"sta": 1546, "time": 3551211, "lat": 40.441551, "lon": -79.938202, "alt": 316, "status": 4}, {"sta": 934, "time": 3683332, "lat": 43.800541, "lon": -90.073509, "alt": 273, "status": 2}, {"sta": 1451, "time": 3825931, "lat": 38.818298, "lon": -77.419899, "alt": 105, "status": 4}, {"sta": 2351, "time": 3838247, "lat": 39.098309, "lon": -77.522064, "alt": 106, "status": 4}, {"sta": 1565, "time": 3936511, "lat": 44.437523, "lon": -88.052505, "alt": 194, "status": 4}, {"sta": 2352, "time": 3965806, "lat": 39.143776, "lon": -77.073463, "alt": 159, "status": 4}, {"sta": 2343, "time": 4146689, "lat": 40.733013, "lon": -77.544647, "alt": 233, "status": 4}, {"sta": 1750, "time": 4243698, "lat": 45.337063, "lon": -89.485497, "alt": 465, "status": 4}, {"sta": 1177, "time": 4290665, "lat": 45.39658, "lon": -88.12439, "alt": 287, "status": 2}, {"sta": 1203, "time": 4405595, "lat": 39.795403, "lon": -75.672989, "alt": 91, "status": 2}, {"sta": 2334, "time": 4458770, "lat": 45.926498, "lon": -89.161949, "alt": 516, "status": 4}, {"sta": 2382, "time": 4489580, "lat": 45.926483, "lon": -89.16198, "alt": 516, "status": 4}, {"sta": 2307, "time": 4545351, "lat": 45.557556, "lon": -93.209183, "alt": 298, "status": 4}, {"sta": 1933, "time": 4859450, "lat": 41.325851, "lon": -74.921974, "alt": 410, "status": 4}], "delay": 8.1}