{"time": 1586713095869480700, "lat": 41.726634, "lon": -84.614214, "alt": 0, "pol": 0, "mds": 9074, "mcg": 163, "status": 0, "region": 3, "sig": [{"sta": 2378, "time": 2683594, "lat": 39.896141, "lon": -75.362137, "alt": 47, "status": 12}, {"sta": 1457, "time": 2684488, "lat": 45.347748, "lon": -75.999527, "alt": 138, "status": 12}, {"sta": 2307, "time": 2707300, "lat": 45.557556, "lon": -93.209183, "alt": 298, "status": 12}, {"sta": 1888, "time": 2709104, "lat": 35.662682, "lon": -79.346863, "alt": 176, "status": 4}, {"sta": 2559, "time": 2745305, "lat": 45.319382, "lon": -75.713577, "alt": 99, "status": 12}, {"sta": 1588, "time": 2754752, "lat": 45.395798, "lon": -75.717903, "alt": 60, "status": 12}, {"sta": 2689, "time": 2763583, "lat": 48.444023, "lon": -89.332916, "alt": 273, "status": 4}, {"sta": 2564, "time": 2828451, "lat": 35.621754, "lon": -78.760498, "alt": 122, "status": 12}, {"sta": 2628, "time": 2857969, "lat": 46.277405, "lon": -75.990685, "alt": 202, "status": 12}, {"sta": 2603, "time": 2892439, "lat": 41.520199, "lon": -74.180962, "alt": 127, "status": 12}, {"sta": 1228, "time": 2927150, "lat": 41.070953, "lon": -74.155174, "alt": 122, "status": 10}, {"sta": 1693, "time": 3012978, "lat": 42.694572, "lon": -73.861237, "alt": 103, "status": 4}, {"sta": 2622, "time": 3029537, "lat": 36.824749, "lon": -76.2033, "alt": 3, "status": 12}, {"sta": 2618, "time": 3073051, "lat": 44.365906, "lon": -73.903053, "alt": 1495, "status": 4}, {"sta": 946, "time": 3098853, "lat": 41.577358, "lon": -73.473312, "alt": 225, "status": 2}, {"sta": 1803, "time": 3157301, "lat": 42.87035, "lon": -73.406662, "alt": 265, "status": 4}, {"sta": 2291, "time": 3251450, "lat": 40.887592, "lon": -83.888977, "alt": 255, "status": 4}, {"sta": 1168, "time": 3265509, "lat": 44.544498, "lon": -73.202644, "alt": 55, "status": 10}, {"sta": 2545, "time": 3283215, "lat": 44.628975, "lon": -73.191483, "alt": 92, "status": 4}, {"sta": 1320, "time": 3321737, "lat": 45.365501, "lon": -73.309105, "alt": 40, "status": 10}, {"sta": 1969, "time": 3473754, "lat": 49.751808, "lon": -77.620392, "alt": 261, "status": 4}, {"sta": 1822, "time": 3577016, "lat": 43.411747, "lon": -71.915886, "alt": 243, "status": 4}, {"sta": 1173, "time": 3642106, "lat": 42.588131, "lon": -71.410667, "alt": 77, "status": 10}, {"sta": 1660, "time": 3657685, "lat": 37.903442, "lon": -78.30706, "alt": 129, "status": 4}, {"sta": 1668, "time": 3671722, "lat": 42.998138, "lon": -71.506699, "alt": 93, "status": 4}, {"sta": 2595, "time": 3705964, "lat": 41.684353, "lon": -98.006622, "alt": 552, "status": 4}, {"sta": 2396, "time": 3718285, "lat": 42.541676, "lon": -71.185944, "alt": 52, "status": 4}, {"sta": 2523, "time": 3724645, "lat": 41.573753, "lon": -71.472427, "alt": 32, "status": 4}, {"sta": 1937, "time": 3773243, "lat": 42.867233, "lon": -71.003937, "alt": 70, "status": 4}, {"sta": 2348, "time": 3829731, "lat": 36.044533, "lon": -95.697792, "alt": 200, "status": 4}, {"sta": 2445, "time": 4016698, "lat": 41.663216, "lon": -70.115341, "alt": 16, "status": 4}, {"sta": 1852, "time": 4024688, "lat": 46.795227, "lon": -71.376358, "alt": 75, "status": 4}, {"sta": 2434, "time": 4206902, "lat": 50.27037, "lon": -73.921913, "alt": 428, "status": 4}, {"sta": 2255, "time": 4295085, "lat": 51.689732, "lon": -76.250954, "alt": 232, "status": 4}, {"sta": 2575, "time": 4302640, "lat": 43.977055, "lon": -69.255951, "alt": 15, "status": 4}, {"sta": 1809, "time": 4430059, "lat": 44.80891, "lon": -68.914398, "alt": 52, "status": 4}, {"sta": 1178, "time": 4533881, "lat": 29.671406, "lon": -82.701393, "alt": 31, "status": 2}, {"sta": 1002, "time": 4728325, "lat": 46.902176, "lon": -100.784859, "alt": 587, "status": 2}, {"sta": 1952, "time": 4821656, "lat": 33.068378, "lon": -96.703217, "alt": 197, "status": 4}, {"sta": 1884, "time": 5089729, "lat": 49.137238, "lon": -68.196098, "alt": 22, "status": 4}], "delay": 8}