{"time": 1586711347485205200, "lat": 31.860519, "lon": -92.934366, "alt": 0, "pol": 0, "mds": 11958, "mcg": 128, "status": 0, "region": 3, "sig": [{"sta": 1860, "time": 1053298, "lat": 29.542299, "lon": -95.105453, "alt": 3, "status": 4}, {"sta": 1952, "time": 1302424, "lat": 33.068378, "lon": -96.703217, "alt": 197, "status": 4}, {"sta": 1824, "time": 1364801, "lat": 29.854717, "lon": -96.527451, "alt": 94, "status": 12}, {"sta": 2348, "time": 1761995, "lat": 36.044533, "lon": -95.697792, "alt": 200, "status": 12}, {"sta": 2302, "time": 3000295, "lat": 37.851643, "lon": -122.242935, "alt": 85, "status": 4}, {"sta": 1178, "time": 3354217, "lat": 29.671406, "lon": -82.701393, "alt": 31, "status": 10}, {"sta": 1823, "time": 3381975, "lat": 40.133369, "lon": -88.207466, "alt": 230, "status": 12}, {"sta": 1439, "time": 3384596, "lat": 38.221153, "lon": -84.817429, "alt": 222, "status": 4}, {"sta": 791, "time": 3404128, "lat": 38.221161, "lon": -84.817444, "alt": 223, "status": 10}, {"sta": 689, "time": 3435732, "lat": 38.221134, "lon": -84.817436, "alt": 226, "status": 2}, {"sta": 1648, "time": 3563841, "lat": 28.19636, "lon": -82.684845, "alt": 13, "status": 12}, {"sta": 2561, "time": 3638681, "lat": 36.552223, "lon": -82.523804, "alt": 381, "status": 12}, {"sta": 681, "time": 3966855, "lat": 41.91127, "lon": -88.357269, "alt": 234, "status": 10}, {"sta": 1888, "time": 4413559, "lat": 35.662682, "lon": -79.346863, "alt": 176, "status": 12}, {"sta": 2543, "time": 4463686, "lat": 41.491772, "lon": -83.720024, "alt": 187, "status": 4}, {"sta": 1199, "time": 4490793, "lat": 41.491783, "lon": -83.720024, "alt": 185, "status": 10}, {"sta": 934, "time": 4505788, "lat": 43.800541, "lon": -90.073509, "alt": 273, "status": 10}, {"sta": 2446, "time": 4519382, "lat": 35.956543, "lon": -79.066269, "alt": 175, "status": 12}, {"sta": 1939, "time": 4523603, "lat": 36.049595, "lon": -79.087204, "alt": 213, "status": 12}, {"sta": 1965, "time": 4841922, "lat": 40.065063, "lon": -105.326729, "alt": 2034, "status": 4}, {"sta": 2520, "time": 4952260, "lat": 39.169876, "lon": -78.979736, "alt": 327, "status": 4}, {"sta": 1660, "time": 4976096, "lat": 37.903442, "lon": -78.30706, "alt": 129, "status": 12}, {"sta": 1750, "time": 5097773, "lat": 45.337063, "lon": -89.485497, "alt": 465, "status": 12}], "delay": 6.6}