{"time": 1586711427395237000, "lat": 51.826152, "lon": -1.753739, "alt": 0, "pol": 0, "mds": 8834, "mcg": 68, "status": 0, "region": 1, "sig": [{"sta": 1637, "time": 84883, "lat": 51.988487, "lon": -2.393044, "alt": 48, "status": 4}, {"sta": 783, "time": 140893, "lat": 51.913029, "lon": -1.154962, "alt": 86, "status": 10}, {"sta": 1288, "time": 197663, "lat": 51.700832, "lon": -0.908408, "alt": 124, "status": 10}, {"sta": 1608, "time": 214010, "lat": 52.170105, "lon": -1.012066, "alt": 141, "status": 12}, {"sta": 1273, "time": 252060, "lat": 52.461922, "lon": -2.167579, "alt": 96, "status": 10}, {"sta": 843, "time": 262375, "lat": 51.309315, "lon": -0.70603, "alt": 109, "status": 2}, {"sta": 2406, "time": 292952, "lat": 52.510281, "lon": -1.173943, "alt": 134, "status": 12}, {"sta": 1338, "time": 298427, "lat": 51.362713, "lon": -2.800544, "alt": 16, "status": 10}, {"sta": 2647, "time": 315329, "lat": 51.825741, "lon": -3.098863, "alt": 105, "status": 12}, {"sta": 2002, "time": 338193, "lat": 51.527527, "lon": -0.384964, "alt": 31, "status": 12}, {"sta": 2576, "time": 354851, "lat": 51.647881, "lon": -0.045645, "alt": 24, "status": 4}, {"sta": 2512, "time": 356673, "lat": 50.915947, "lon": -1.303907, "alt": 29, "status": 12}, {"sta": 2447, "time": 364953, "lat": 51.785275, "lon": -0.187061, "alt": 72, "status": 12}, {"sta": 2267, "time": 367828, "lat": 50.864487, "lon": -1.403687, "alt": 8, "status": 12}, {"sta": 2413, "time": 381874, "lat": 51.395275, "lon": -0.260615, "alt": 27, "status": 12}, {"sta": 2007, "time": 444668, "lat": 52.560532, "lon": -0.243721, "alt": 14, "status": 12}, {"sta": 1622, "time": 450931, "lat": 52.621422, "lon": -0.281652, "alt": 14, "status": 12}, {"sta": 1354, "time": 473988, "lat": 52.456066, "lon": 0.057497, "alt": 5, "status": 10}, {"sta": 2080, "time": 502961, "lat": 50.929703, "lon": -0.133519, "alt": 45, "status": 12}, {"sta": 1545, "time": 537873, "lat": 53.244858, "lon": -2.136098, "alt": 182, "status": 10}, {"sta": 2442, "time": 553790, "lat": 50.698082, "lon": -3.290698, "alt": 25, "status": 12}, {"sta": 1039, "time": 556525, "lat": 52.241779, "lon": 0.582665, "alt": 92, "status": 10}, {"sta": 1075, "time": 621354, "lat": 53.396526, "lon": -2.669355, "alt": 17, "status": 10}, {"sta": 1472, "time": 656556, "lat": 53.396545, "lon": -2.669358, "alt": 30, "status": 4}, {"sta": 1819, "time": 702245, "lat": 52.057968, "lon": 1.268417, "alt": 26, "status": 4}, {"sta": 1968, "time": 728547, "lat": 51.371201, "lon": 1.301205, "alt": 16, "status": 4}, {"sta": 1620, "time": 763506, "lat": 53.858353, "lon": -1.840078, "alt": 109, "status": 4}, {"sta": 1061, "time": 774592, "lat": 50.408165, "lon": -4.172679, "alt": 90, "status": 2}, {"sta": 1896, "time": 1075456, "lat": 52.183041, "lon": -6.383036, "alt": 9, "status": 4}, {"sta": 1627, "time": 1116066, "lat": 54.783264, "lon": -2.421839, "alt": 433, "status": 4}, {"sta": 1283, "time": 1363113, "lat": 54.634159, "lon": -5.672031, "alt": 43, "status": 2}, {"sta": 733, "time": 1615372, "lat": 50.754189, "lon": 4.982888, "alt": 51, "status": 2}], "delay": 5.5}